mathicsscript/__init__.py
mathicsscript/__main__.py
mathicsscript/asymptote.py
mathicsscript/bindkeys.py
mathicsscript/completion.py
mathicsscript/config.asy
mathicsscript/fake_psviewer.py
mathicsscript/format-next.py
mathicsscript/format-try.py
mathicsscript/format.py
mathicsscript/interrupt.py
mathicsscript/settings.py
mathicsscript/termshell.py
mathicsscript/termshell_gnu.py
mathicsscript/termshell_prompt.py
mathicsscript/user-settings.m
mathicsscript/version.py
mathicsscript/autoload/settings.m
mathicsscript/data/inputrc-no-unicode
mathicsscript/data/inputrc-unicode
mathicsscript/data/mma-tables.json
mathicsscript-9.0.0.dist-info/licenses/COPYING.txt
test/__init__.py
test/helper.py
test/test_completion.py
test/test_returncode.py
test/test_settings.py
test/data/recursive-gcd.m
mathicsscript-9.0.0.dist-info/METADATA
mathicsscript-9.0.0.dist-info/WHEEL
mathicsscript-9.0.0.dist-info/entry_points.txt
mathicsscript-9.0.0.dist-info/top_level.txt
mathicsscript-9.0.0.dist-info/RECORD
