Metadata-Version: 2.4
Name: mathicsscript
Version: 9.0.0
Summary: Command-line interface to Mathics3
Maintainer: Mathics3 Group
License-Expression: GPL-3.0-or-later
Project-URL: Homepage, https://mathics.org/
Keywords: Mathematica,Wolfram,Interpreter,Shell,Math,CAS
Classifier: Intended Audience :: Developers
Classifier: Intended Audience :: Science/Research
Classifier: Programming Language :: Python
Classifier: Programming Language :: Python :: 3.10
Classifier: Programming Language :: Python :: 3.11
Classifier: Programming Language :: Python :: 3.12
Classifier: Programming Language :: Python :: 3.13
Classifier: Programming Language :: Python :: Implementation :: CPython
Classifier: Programming Language :: Python :: Implementation :: PyPy
Classifier: Topic :: Scientific/Engineering
Classifier: Topic :: Scientific/Engineering :: Mathematics
Classifier: Topic :: Software Development :: Interpreters
Requires-Python: >=3.10
License-File: COPYING.txt
Requires-Dist: Mathics_Scanner>=2.0.0
Requires-Dist: Mathics3>=9.0.0
Requires-Dist: click>=8.0.0
Requires-Dist: colorama
Requires-Dist: columnize
Requires-Dist: networkx
Requires-Dist: prompt_toolkit>=3.0.18
Requires-Dist: Pygments>=2.9.0
Requires-Dist: mathics_pygments>=1.0.2
Requires-Dist: term-background>=1.0.1
Provides-Extra: dev
Requires-Dist: pytest; extra == "dev"
Provides-Extra: full
Requires-Dist: PyYAML; extra == "full"
Requires-Dist: PyQT6; extra == "full"
Requires-Dist: cairosvg; extra == "full"
Requires-Dist: cson; extra == "full"
Requires-Dist: matplotlib; extra == "full"
Dynamic: license-file
